xarrayhdf/__init__.py
xarrayhdf/__version__
xarray_hdf-0.1.0.dist-info/LICENSE
xarray_hdf-0.1.0.dist-info/METADATA
xarray_hdf-0.1.0.dist-info/WHEEL
xarray_hdf-0.1.0.dist-info/top_level.txt
xarray_hdf-0.1.0.dist-info/RECORD
