Metadata-Version: 2.1
Name: xarray-hdf
Version: 0.1.0
Summary: Store xarray Datasets using PyTables, with support for attributes.
Home-page: https://github.com/otaithleigh/xarray-hdf
Author: Peter Talley
Author-email: peterctalley@gmail.com
License: MIT
Platform: UNKNOWN
Requires-Python: >=3.7
Requires-Dist: h5py
Requires-Dist: pandas
Requires-Dist: tables
Requires-Dist: xarray
